naff_link/__init__.py
naff_link/events.py
naff_link/main.py
naff_link-0.0.1.dist-info/METADATA
naff_link-0.0.1.dist-info/WHEEL
naff_link-0.0.1.dist-info/top_level.txt
naff_link-0.0.1.dist-info/RECORD
