Metadata-Version: 2.1
Name: naff-link
Version: 0.0.1
Summary: A Lavalink.py wrapper for Naff
Home-page: https://github.com/NAFTeam/Naff-Link
Author: LordOfPolls
Author-email: dev@lordofpolls.com
License: UNKNOWN
Platform: UNKNOWN
Classifier: Programming Language :: Python :: 3
Classifier: License :: OSI Approved :: MIT License
Classifier: Operating System :: OS Independent
Requires-Python: >=3.10
Requires-Dist: lavalink
Requires-Dist: naff
